acldpy/__init__.py
acldpy/calc_cld.py
acldpy/cld_utils.py
acldpy-0.2.0.dist-info/licenses/LICENSE
acldpy-0.2.0.dist-info/METADATA
acldpy-0.2.0.dist-info/WHEEL
acldpy-0.2.0.dist-info/top_level.txt
acldpy-0.2.0.dist-info/RECORD
