Metadata-Version: 2.4
Name: acldpy
Version: 0.2.0
License-File: LICENSE
Requires-Dist: numpy>=1.13.1
Dynamic: description
Dynamic: description-content-type
Dynamic: license-file
Dynamic: requires-dist
